csirtgsdk/__init__.py
csirtgsdk/_version.py
csirtgsdk/client.py
csirtgsdk/constants.py
csirtgsdk/feed.py
csirtgsdk/indicator.py
csirtgsdk/search.py
csirtgsdk/utils.py
csirtgsdk/format/__init__.py
csirtgsdk/format/format_csv.py
csirtgsdk/format/format_json.py
csirtgsdk/format/format_stix.py
csirtgsdk/format/table.py
csirtgsdk/format/zbro.py
csirtgsdk-0.0.0a6.dist-info/DESCRIPTION.rst
csirtgsdk-0.0.0a6.dist-info/METADATA
csirtgsdk-0.0.0a6.dist-info/RECORD
csirtgsdk-0.0.0a6.dist-info/WHEEL
csirtgsdk-0.0.0a6.dist-info/entry_points.txt
csirtgsdk-0.0.0a6.dist-info/metadata.json
csirtgsdk-0.0.0a6.dist-info/top_level.txt
test/__init__.py
test/test_client.py
test/test_feed.py
test/test_feed_live.py
test/test_format_stix.py
test/test_indicator.py
test/test_indicator_attachment_live.py
test/test_search.py
test/test_search_live.py
test/format/__init__.py
test/format/test_zbro.py
